i3_xkb_switcher/__init__.py
i3_xkb_switcher/switcher.py
i3_xkb_switcher-0.2.1.dist-info/entry_points.txt
i3_xkb_switcher-0.2.1.dist-info/LICENSE
i3_xkb_switcher-0.2.1.dist-info/WHEEL
i3_xkb_switcher-0.2.1.dist-info/METADATA
i3_xkb_switcher-0.2.1.dist-info/RECORD
