Metadata-Version: 2.1
Name: i3-xkb-switcher
Version: 0.2.1
Summary: Keyboard layout switcher for i3 windows
Home-page: https://github.com/inn0kenty/i3-xkb-switcher
License: MIT
Author: Innokenty Lebedev
Requires-Python: >=3.7,<4.0
Classifier: License :: OSI Approved :: MIT License
Classifier: Programming Language :: Python :: 3
Classifier: Programming Language :: Python :: 3.7
Classifier: Programming Language :: Python :: 3.8
Requires-Dist: i3ipc (>=2.1.1,<3.0.0)
Requires-Dist: xkbgroup (>=0.2.0,<0.3.0)
Project-URL: Repository, https://github.com/inn0kenty/i3-xkb-switcher
